vim_python_framework/__init__.py
vim_python_framework/create_plugin.py
vim_python_framework/include/__init__.py
vim_python_framework/include/mymodule.py
vim_python_framework/src/__init__.py
vim_python_framework/src/calculator.py
vim_python_framework-1.0.0.dist-info/METADATA
vim_python_framework-1.0.0.dist-info/WHEEL
vim_python_framework-1.0.0.dist-info/entry_points.txt
vim_python_framework-1.0.0.dist-info/top_level.txt
vim_python_framework-1.0.0.dist-info/RECORD
