Metadata-Version: 2.1
Name: vim-python-framework
Version: 1.0.0
Summary: ('A framework to easily create Vim plugins using Python',)
Author: David Kennedy S. Araujo
Author-email: software@davidkennedy.dev
